hackernewslib/__init__.py
hackernewslib/articles.py
hackernewslib/clients.py
hackernewslib/exceptions.py
hackernewslib/loaders.py
hackernewslib/mixins.py
hackernewslib/models.py
hackernewslib/schemas.py
hackernewslib-0.1.0.dist-info/LICENSE
hackernewslib-0.1.0.dist-info/METADATA
hackernewslib-0.1.0.dist-info/WHEEL
hackernewslib-0.1.0.dist-info/top_level.txt
hackernewslib-0.1.0.dist-info/RECORD
